easyfactory/__init__.py
easyfactory/auto_factory.py
easyfactory/pydantic.py
easyfactory/sqlalchemy.py
easyfactory/utils.py
EasyFactory-1.4.2.dist-info/LICENSE
EasyFactory-1.4.2.dist-info/METADATA
EasyFactory-1.4.2.dist-info/WHEEL
EasyFactory-1.4.2.dist-info/top_level.txt
EasyFactory-1.4.2.dist-info/RECORD
