Metadata-Version: 2.1
Name: EasyFactory
Version: 1.4.2
Summary: EasyFactory is a wrapper above FactoryBoy to allow the generation of Factory class with mandatory parameter filed.
Author-email: Baboin Arthur <baboin.arthur@gmail.com>
Project-URL: Homepage, https://gitlab.com/Tagashy/easyfactory
Project-URL: Documentation, https://tagashy.gitlab.io/easyfactory/
Project-URL: Repository, https://gitlab.com/Tagashy/easyfactory.git
Project-URL: Issues, https://gitlab.com/Tagashy/easyfactory/issues
Project-URL: Bug Tracker, https://gitlab.com/Tagashy/easyfactory/issues
Classifier: Development Status :: 4 - Beta
Classifier: Intended Audience :: Developers
Classifier: Topic :: Software Development :: Code Generators
Classifier: Topic :: Software Development :: Libraries
Classifier: Programming Language :: Python :: 3.12
Classifier: License :: OSI Approved :: MIT License
Classifier: Operating System :: OS Independent
Requires-Python: >=3.12
License-File: LICENSE
Requires-Dist: factory_boy~=3.3.0
Requires-Dist: SQLAlchemy~=2.0.36
Requires-Dist: pydantic~=2.8.2
Provides-Extra: tests
Requires-Dist: pytest~=8.0.2; extra == "tests"
Requires-Dist: pytest-cov~=4.1.0; extra == "tests"
Requires-Dist: pytest-mock~=3.12.0; extra == "tests"
